<?xml version="1.0" encoding="utf-8"?>
<!DOCTYPE hibernate-mapping PUBLIC "-//Hibernate/Hibernate Mapping DTD 3.0//EN"
"http://hibernate.sourceforge.net/hibernate-mapping-3.0.dtd">
<!-- 
    Mapping file autogenerated by MyEclipse Persistence Tools
-->
<hibernate-mapping>
    <class name="com.gopawpaw.erp.hibernate.c.CclCtrl" table="ccl_ctrl" schema="PUB" catalog="MFGPROD">
        <id name="cclDomain" type="java.lang.String">
            <column name="ccl_domain" length="8" />
            <generator class="native" />
        </id>
        <property name="cclQadi01" type="java.lang.Integer">
            <column name="ccl__qadi01" not-null="true" />
        </property>
        <property name="cclContActive" type="java.lang.Boolean">
            <column name="ccl_cont_active" not-null="true" />
        </property>
        <property name="cclLineActive" type="java.lang.Boolean">
            <column name="ccl_line_active" not-null="true" />
        </property>
        <property name="cclEditLcShipper" type="java.lang.Boolean">
            <column name="ccl_edit_lc_shipper" not-null="true" />
        </property>
        <property name="cclCcInvoice" type="java.lang.Boolean">
            <column name="ccl_cc_invoice" not-null="true" />
        </property>
        <property name="cclLcInvoice" type="java.lang.Boolean">
            <column name="ccl_lc_invoice" not-null="true" />
        </property>
        <property name="cclCcAsn" type="java.lang.Boolean">
            <column name="ccl_cc_asn" not-null="true" />
        </property>
        <property name="cclLcAsn" type="java.lang.Boolean">
            <column name="ccl_lc_asn" not-null="true" />
        </property>
        <property name="cclChargeType" type="java.lang.String">
            <column name="ccl_charge_type" length="80" not-null="true" />
        </property>
        <property name="cclModUserid" type="java.lang.String">
            <column name="ccl_mod_userid" length="80" not-null="true" />
        </property>
        <property name="cclModDate" type="java.util.Date">
            <column name="ccl_mod_date" length="4" />
        </property>
        <property name="cclUserc01" type="java.lang.String">
            <column name="ccl_userc01" length="80" not-null="true" />
        </property>
        <property name="cclUserc02" type="java.lang.String">
            <column name="ccl_userc02" length="80" not-null="true" />
        </property>
        <property name="cclQadc01" type="java.lang.String">
            <column name="ccl__qadc01" length="80" not-null="true" />
        </property>
        <property name="cclQadc02" type="java.lang.String">
            <column name="ccl__qadc02" length="80" not-null="true" />
        </property>
        <property name="oidCclCtrl" type="java.lang.Double">
            <column name="oid_ccl_ctrl" precision="38" scale="10" not-null="true" />
        </property>
    </class>
</hibernate-mapping>
