<?xml version="1.0" encoding="utf-8"?>
<!DOCTYPE hibernate-mapping PUBLIC "-//Hibernate/Hibernate Mapping DTD 3.0//EN"
"http://hibernate.sourceforge.net/hibernate-mapping-3.0.dtd">
<!-- 
    Mapping file autogenerated by MyEclipse Persistence Tools
-->
<hibernate-mapping>
    <class name="com.gopawpaw.erp.hibernate.f.FsuMstr" table="fsu_mstr" schema="PUB" catalog="MFGPROD">
        <composite-id name="id" class="com.gopawpaw.erp.hibernate.f.FsuMstrId">
            <key-property name="fsuDomain" type="java.lang.String">
                <column name="fsu_domain" length="8" />
            </key-property>
            <key-property name="fsuUserid" type="java.lang.String">
                <column name="fsu_userid" length="80" />
            </key-property>
        </composite-id>
        <property name="fsuCaTimeWnd" type="java.lang.Boolean">
            <column name="fsu_ca_time_wnd" />
        </property>
        <property name="fsuCaWoWnd" type="java.lang.Boolean">
            <column name="fsu_ca_wo_wnd" />
        </property>
        <property name="fsuDfltPri" type="java.lang.Integer">
            <column name="fsu_dflt_pri" />
        </property>
        <property name="fsuDfltQue" type="java.lang.String">
            <column name="fsu_dflt_que" length="80" />
        </property>
        <property name="fsuEscDflt" type="java.lang.String">
            <column name="fsu_esc_dflt" length="80" />
        </property>
        <property name="fsuQueProg" type="java.lang.Integer">
            <column name="fsu_que_prog" />
        </property>
        <property name="fsuQuoteQue" type="java.lang.String">
            <column name="fsu_quote_que" length="80" />
        </property>
        <property name="fsuTimezone" type="java.lang.String">
            <column name="fsu_timezone" length="80" />
        </property>
        <property name="fsuQadc02" type="java.lang.String">
            <column name="fsu__qadc02" length="80" />
        </property>
        <property name="fsuQadc03" type="java.lang.String">
            <column name="fsu__qadc03" length="80" />
        </property>
        <property name="fsuQadc04" type="java.lang.String">
            <column name="fsu__qadc04" length="80" />
        </property>
        <property name="fsuQadc05" type="java.lang.String">
            <column name="fsu__qadc05" length="80" />
        </property>
        <property name="fsuQadl01" type="java.lang.Boolean">
            <column name="fsu__qadl01" />
        </property>
        <property name="fsuQadl02" type="java.lang.Boolean">
            <column name="fsu__qadl02" />
        </property>
        <property name="fsuQadl03" type="java.lang.Boolean">
            <column name="fsu__qadl03" />
        </property>
        <property name="fsuQadl04" type="java.lang.Boolean">
            <column name="fsu__qadl04" />
        </property>
        <property name="fsuQadl05" type="java.lang.Boolean">
            <column name="fsu__qadl05" />
        </property>
        <property name="fsuQadi01" type="java.lang.Integer">
            <column name="fsu__qadi01" />
        </property>
        <property name="fsuQadi02" type="java.lang.Integer">
            <column name="fsu__qadi02" />
        </property>
        <property name="fsuQadi03" type="java.lang.Integer">
            <column name="fsu__qadi03" />
        </property>
        <property name="fsuQadi04" type="java.lang.Integer">
            <column name="fsu__qadi04" />
        </property>
        <property name="fsuQadi05" type="java.lang.Integer">
            <column name="fsu__qadi05" />
        </property>
        <property name="fsuUser1" type="java.lang.String">
            <column name="fsu_user1" length="80" />
        </property>
        <property name="fsuUser2" type="java.lang.String">
            <column name="fsu_user2" length="80" />
        </property>
        <property name="fsuQadc06" type="java.lang.String">
            <column name="fsu__qadc06" length="80" />
        </property>
        <property name="fsuQadt01" type="java.util.Date">
            <column name="fsu__qadt01" length="4" />
        </property>
        <property name="fsuQadt02" type="java.util.Date">
            <column name="fsu__qadt02" length="4" />
        </property>
        <property name="oidFsuMstr" type="java.lang.Double">
            <column name="oid_fsu_mstr" precision="38" scale="10" not-null="true" />
        </property>
    </class>
</hibernate-mapping>
