<?xml version="1.0" encoding="utf-8"?>
<!DOCTYPE hibernate-mapping PUBLIC "-//Hibernate/Hibernate Mapping DTD 3.0//EN"
"http://hibernate.sourceforge.net/hibernate-mapping-3.0.dtd">
<!-- 
    Mapping file autogenerated by MyEclipse Persistence Tools
-->
<hibernate-mapping>
    <class name="com.gopawpaw.erp.hibernate.l.LpmMstr" table="lpm_mstr" schema="PUB" catalog="MFGPROD">
        <id name="lpmProduct" type="java.lang.String">
            <column name="lpm_product" length="30" />
            <generator class="native" />
        </id>
        <property name="lpmDesc" type="java.lang.String">
            <column name="lpm_desc" length="80" not-null="true" />
        </property>
        <property name="lpmLicReq" type="java.lang.Boolean">
            <column name="lpm_lic_req" not-null="true" />
        </property>
        <property name="lpmModUserid" type="java.lang.String">
            <column name="lpm_mod_userid" length="80" not-null="true" />
        </property>
        <property name="lpmModDate" type="java.util.Date">
            <column name="lpm_mod_date" length="4" not-null="true" />
        </property>
        <property name="lpmQadc01" type="java.lang.String">
            <column name="lpm__qadc01" length="80" not-null="true" />
        </property>
        <property name="lpmQadc02" type="java.lang.String">
            <column name="lpm__qadc02" length="80" not-null="true" />
        </property>
        <property name="lpmQadd01" type="java.lang.Double">
            <column name="lpm__qadd01" precision="38" scale="10" not-null="true" />
        </property>
        <property name="lpmQadt01" type="java.util.Date">
            <column name="lpm__qadt01" length="4" />
        </property>
        <property name="lpmVerList" type="java.lang.String">
            <column name="lpm_ver_list" length="80" not-null="true" />
        </property>
        <property name="oidLpmMstr" type="java.lang.Double">
            <column name="oid_lpm_mstr" precision="38" scale="10" not-null="true" />
        </property>
    </class>
</hibernate-mapping>
