<?xml version="1.0" encoding="utf-8"?>
<!DOCTYPE hibernate-mapping PUBLIC "-//Hibernate/Hibernate Mapping DTD 3.0//EN"
"http://hibernate.sourceforge.net/hibernate-mapping-3.0.dtd">
<!-- 
    Mapping file autogenerated by MyEclipse Persistence Tools
-->
<hibernate-mapping>
    <class name="com.gopawpaw.erp.hibernate.s.ShpHist" table="shp_hist" schema="PUB" catalog="MFGPROD">
        <composite-id name="id" class="com.gopawpaw.erp.hibernate.s.ShpHistId">
            <key-property name="shpDomain" type="java.lang.String">
                <column name="shp_domain" length="8" />
            </key-property>
            <key-property name="shpTranId" type="java.lang.Integer">
                <column name="shp_tran_id" />
            </key-property>
        </composite-id>
        <property name="shpNbr" type="java.lang.String">
            <column name="shp_nbr" length="80" not-null="true" />
        </property>
        <property name="shpLine" type="java.lang.Integer">
            <column name="shp_line" not-null="true" />
        </property>
        <property name="shpShipfrom" type="java.lang.String">
            <column name="shp_shipfrom" length="80" not-null="true" />
        </property>
        <property name="shpPart" type="java.lang.String">
            <column name="shp_part" length="30" not-null="true" />
        </property>
        <property name="shpCustPart" type="java.lang.String">
            <column name="shp_cust_part" length="80" not-null="true" />
        </property>
        <property name="shpOpenQty" type="java.lang.Double">
            <column name="shp_open_qty" precision="38" scale="10" not-null="true" />
        </property>
        <property name="shpExtPrice" type="java.lang.Double">
            <column name="shp_ext_price" precision="38" scale="10" not-null="true" />
        </property>
        <property name="shpDueDate" type="java.util.Date">
            <column name="shp_due_date" length="4" />
        </property>
        <property name="shpReqDate" type="java.util.Date">
            <column name="shp_req_date" length="4" />
        </property>
        <property name="shpPerfDate" type="java.util.Date">
            <column name="shp_perf_date" length="4" />
        </property>
        <property name="shpShipDate" type="java.util.Date">
            <column name="shp_ship_date" length="4" />
        </property>
        <property name="shpCust" type="java.lang.String">
            <column name="shp_cust" length="80" not-null="true" />
        </property>
        <property name="shpShipQty" type="java.lang.Double">
            <column name="shp_ship_qty" precision="38" scale="10" not-null="true" />
        </property>
        <property name="shpShipPrice" type="java.lang.Double">
            <column name="shp_ship_price" precision="38" scale="10" not-null="true" />
        </property>
        <property name="shpAbsId" type="java.lang.String">
            <column name="shp_abs_id" length="30" not-null="true" />
        </property>
        <property name="shpInclude" type="java.lang.Boolean">
            <column name="shp_include" not-null="true" />
        </property>
        <property name="shpModDate" type="java.util.Date">
            <column name="shp_mod_date" length="4" not-null="true" />
        </property>
        <property name="shpModUserid" type="java.lang.String">
            <column name="shp_mod_userid" length="80" not-null="true" />
        </property>
        <property name="shpShipto" type="java.lang.String">
            <column name="shp_shipto" length="80" not-null="true" />
        </property>
        <property name="shpShipTime" type="java.lang.String">
            <column name="shp_ship_time" length="30" not-null="true" />
        </property>
        <property name="shpRelId" type="java.lang.String">
            <column name="shp_rel_id" length="80" not-null="true" />
        </property>
        <property name="shpCmtindx" type="java.lang.Integer">
            <column name="shp_cmtindx" not-null="true" />
        </property>
        <property name="shpOrderCategory" type="java.lang.String">
            <column name="shp_order_category" length="80" not-null="true" />
        </property>
        <property name="shpCustomerSource" type="java.lang.String">
            <column name="shp_customer_source" length="30" not-null="true" />
        </property>
        <property name="shpShipUm" type="java.lang.String">
            <column name="shp_ship_um" length="30" not-null="true" />
        </property>
        <property name="shpShipUmConv" type="java.lang.Double">
            <column name="shp_ship_um_conv" precision="38" scale="10" not-null="true" />
        </property>
        <property name="shpCurrency" type="java.lang.String">
            <column name="shp_currency" length="30" not-null="true" />
        </property>
        <property name="shpOrdUm" type="java.lang.String">
            <column name="shp_ord_um" length="30" not-null="true" />
        </property>
        <property name="shpOrdUmConv" type="java.lang.Double">
            <column name="shp_ord_um_conv" precision="38" scale="10" not-null="true" />
        </property>
        <property name="shpSchedTime" type="java.lang.String">
            <column name="shp_sched_time" length="30" not-null="true" />
        </property>
        <property name="shpDoReq" type="java.lang.String">
            <column name="shp_do_req" length="80" not-null="true" />
        </property>
        <property name="shpQadc01" type="java.lang.String">
            <column name="shp__qadc01" length="80" not-null="true" />
        </property>
        <property name="shpQadc02" type="java.lang.String">
            <column name="shp__qadc02" length="80" not-null="true" />
        </property>
        <property name="shpUser1" type="java.lang.String">
            <column name="shp_user1" length="80" not-null="true" />
        </property>
        <property name="shpUser2" type="java.lang.String">
            <column name="shp_user2" length="80" not-null="true" />
        </property>
        <property name="shpQtyPct" type="java.lang.Double">
            <column name="shp_qty_pct" precision="38" scale="10" not-null="true" />
        </property>
        <property name="oidShpHist" type="java.lang.Double">
            <column name="oid_shp_hist" precision="38" scale="10" not-null="true" />
        </property>
    </class>
</hibernate-mapping>
