<?xml version="1.0" encoding="utf-8"?>
<!DOCTYPE hibernate-mapping PUBLIC "-//Hibernate/Hibernate Mapping DTD 3.0//EN"
"http://hibernate.sourceforge.net/hibernate-mapping-3.0.dtd">
<!-- 
    Mapping file autogenerated by MyEclipse Persistence Tools
-->
<hibernate-mapping>
    <class name="com.gopawpaw.erp.hibernate.a.AbscDet" table="absc_det" schema="PUB" catalog="MFGPROD">
        <composite-id name="id" class="com.gopawpaw.erp.hibernate.a.AbscDetId">
            <key-property name="abscDomain" type="java.lang.String">
                <column name="absc_domain" length="8" />
            </key-property>
            <key-property name="abscAbsId" type="java.lang.String">
                <column name="absc_abs_id" length="30" />
            </key-property>
            <key-property name="abscSeq" type="java.lang.Integer">
                <column name="absc_seq" />
            </key-property>
        </composite-id>
        <property name="abscCarrier" type="java.lang.String">
            <column name="absc_carrier" length="80" not-null="true" />
        </property>
        <property name="abscUser1" type="java.lang.String">
            <column name="absc_user1" length="80" />
        </property>
        <property name="abscUser2" type="java.lang.String">
            <column name="absc_user2" length="80" />
        </property>
        <property name="abscQadc01" type="java.lang.String">
            <column name="absc__qadc01" length="80" />
        </property>
        <property name="oidAbscDet" type="java.lang.Double">
            <column name="oid_absc_det" precision="38" scale="10" not-null="true" />
        </property>
    </class>
</hibernate-mapping>
