<?xml version="1.0" encoding="utf-8"?>
<!DOCTYPE hibernate-mapping PUBLIC "-//Hibernate/Hibernate Mapping DTD 3.0//EN"
"http://hibernate.sourceforge.net/hibernate-mapping-3.0.dtd">
<!-- 
    Mapping file autogenerated by MyEclipse Persistence Tools
-->
<hibernate-mapping>
    <class name="com.gopawpaw.erp.hibernate.a.AnMstr" table="an_mstr" schema="PUB" catalog="MFGPROD">
        <composite-id name="id" class="com.gopawpaw.erp.hibernate.a.AnMstrId">
            <key-property name="anDomain" type="java.lang.String">
                <column name="an_domain" length="8" />
            </key-property>
            <key-property name="anType" type="java.lang.String">
                <column name="an_type" length="30" />
            </key-property>
            <key-property name="anCode" type="java.lang.String">
                <column name="an_code" length="30" />
            </key-property>
        </composite-id>
        <property name="anUserid" type="java.lang.String">
            <column name="an_userid" length="80" />
        </property>
        <property name="anCmtindx" type="java.lang.Integer">
            <column name="an_cmtindx" />
        </property>
        <property name="anDesc" type="java.lang.String">
            <column name="an_desc" length="80" />
        </property>
        <property name="anSecGroup" type="java.lang.String">
            <column name="an_sec_group" length="80" />
        </property>
        <property name="anModDate" type="java.util.Date">
            <column name="an_mod_date" length="4" />
        </property>
        <property name="anActive" type="java.lang.Boolean">
            <column name="an_active" />
        </property>
        <property name="anUser1" type="java.lang.String">
            <column name="an_user1" length="80" />
        </property>
        <property name="anUser2" type="java.lang.String">
            <column name="an_user2" length="80" />
        </property>
        <property name="anQadc01" type="java.lang.String">
            <column name="an__qadc01" length="80" />
        </property>
        <property name="anQadd01" type="java.lang.Double">
            <column name="an__qadd01" precision="38" scale="10" />
        </property>
        <property name="oidAnMstr" type="java.lang.Double">
            <column name="oid_an_mstr" precision="38" scale="10" not-null="true" />
        </property>
    </class>
</hibernate-mapping>
