<?xml version="1.0" encoding="utf-8"?>
<!DOCTYPE hibernate-mapping PUBLIC "-//Hibernate/Hibernate Mapping DTD 3.0//EN"
"http://hibernate.sourceforge.net/hibernate-mapping-3.0.dtd">
<!-- 
    Mapping file autogenerated by MyEclipse Persistence Tools
-->
<hibernate-mapping>
    <class name="com.gopawpaw.erp.hibernate.p.PjsxDet" table="pjsx_det" schema="PUB" catalog="MFGPROD">
        <composite-id name="id" class="com.gopawpaw.erp.hibernate.p.PjsxDetId">
            <key-property name="pjsxDomain" type="java.lang.String">
                <column name="pjsx_domain" length="8" />
            </key-property>
            <key-property name="pjsxNbr" type="java.lang.String">
                <column name="pjsx_nbr" length="80" />
            </key-property>
            <key-property name="pjsxLine" type="java.lang.Integer">
                <column name="pjsx_line" />
            </key-property>
        </composite-id>
        <property name="pjsxPrjNbr" type="java.lang.String">
            <column name="pjsx_prj_nbr" length="80" not-null="true" />
        </property>
        <property name="pjsxPjsLine" type="java.lang.Integer">
            <column name="pjsx_pjs_line" not-null="true" />
        </property>
        <property name="pjsxDate" type="java.util.Date">
            <column name="pjsx_date" length="4" />
        </property>
        <property name="pjsxDefWs" type="java.lang.String">
            <column name="pjsx_def_ws" length="80" not-null="true" />
        </property>
        <property name="pjsxEndDate" type="java.util.Date">
            <column name="pjsx_end_date" length="4" />
        </property>
        <property name="pjsxIntStat" type="java.lang.String">
            <column name="pjsx_int_stat" length="80" not-null="true" />
        </property>
        <property name="pjsxLoc" type="java.lang.String">
            <column name="pjsx_loc" length="80" not-null="true" />
        </property>
        <property name="pjsxQtyDemand" type="java.lang.Double">
            <column name="pjsx_qty_demand" precision="38" scale="10" not-null="true" />
        </property>
        <property name="pjsxQtyOrd" type="java.lang.Double">
            <column name="pjsx_qty_ord" precision="38" scale="10" not-null="true" />
        </property>
        <property name="pjsxQtyInProg" type="java.lang.Double">
            <column name="pjsx_qty_in_prog" precision="38" scale="10" not-null="true" />
        </property>
        <property name="pjsxQtyIss" type="java.lang.Double">
            <column name="pjsx_qty_iss" precision="38" scale="10" not-null="true" />
        </property>
        <property name="pjsxSite" type="java.lang.String">
            <column name="pjsx_site" length="80" not-null="true" />
        </property>
        <property name="pjsxSoNbr" type="java.lang.String">
            <column name="pjsx_so_nbr" length="80" not-null="true" />
        </property>
        <property name="pjsxSodLine" type="java.lang.Integer">
            <column name="pjsx_sod_line" not-null="true" />
        </property>
        <property name="pjsxStartDate" type="java.util.Date">
            <column name="pjsx_start_date" length="4" />
        </property>
        <property name="pjsxType" type="java.lang.String">
            <column name="pjsx_type" length="30" not-null="true" />
        </property>
        <property name="pjsxModDate" type="java.util.Date">
            <column name="pjsx_mod_date" length="4" not-null="true" />
        </property>
        <property name="pjsxModUserid" type="java.lang.String">
            <column name="pjsx_mod_userid" length="80" not-null="true" />
        </property>
        <property name="pjsxUser1" type="java.lang.String">
            <column name="pjsx_user1" length="80" />
        </property>
        <property name="pjsxUser2" type="java.lang.String">
            <column name="pjsx_user2" length="80" />
        </property>
        <property name="pjsxDec01" type="java.lang.Double">
            <column name="pjsx__dec01" precision="38" scale="10" />
        </property>
        <property name="pjsxLog01" type="java.lang.Boolean">
            <column name="pjsx__log01" />
        </property>
        <property name="pjsxDte01" type="java.util.Date">
            <column name="pjsx__dte01" length="4" />
        </property>
        <property name="pjsxQadc01" type="java.lang.String">
            <column name="pjsx__qadc01" length="80" />
        </property>
        <property name="pjsxQadc02" type="java.lang.String">
            <column name="pjsx__qadc02" length="80" />
        </property>
        <property name="pjsxQadd01" type="java.lang.Double">
            <column name="pjsx__qadd01" precision="38" scale="10" />
        </property>
        <property name="pjsxQadi01" type="java.lang.Integer">
            <column name="pjsx__qadi01" />
        </property>
        <property name="pjsxQadl01" type="java.lang.Boolean">
            <column name="pjsx__qadl01" />
        </property>
        <property name="pjsxQadt01" type="java.util.Date">
            <column name="pjsx__qadt01" length="4" />
        </property>
        <property name="oidPjsxDet" type="java.lang.Double">
            <column name="oid_pjsx_det" precision="38" scale="10" not-null="true" />
        </property>
    </class>
</hibernate-mapping>
