<?xml version="1.0" encoding="utf-8"?>
<!DOCTYPE hibernate-mapping PUBLIC "-//Hibernate/Hibernate Mapping DTD 3.0//EN"
"http://hibernate.sourceforge.net/hibernate-mapping-3.0.dtd">
<!-- 
    Mapping file autogenerated by MyEclipse Persistence Tools
-->
<hibernate-mapping>
    <class name="com.gopawpaw.erp.hibernate.m.MaMstr" table="ma_mstr" schema="PUB" catalog="MFGPROD">
        <composite-id name="id" class="com.gopawpaw.erp.hibernate.m.MaMstrId">
            <key-property name="maDomain" type="java.lang.String">
                <column name="ma_domain" length="8" />
            </key-property>
            <key-property name="maEntity" type="java.lang.String">
                <column name="ma_entity" length="30" />
            </key-property>
            <key-property name="maTrType" type="java.lang.String">
                <column name="ma_tr_type" length="30" />
            </key-property>
            <key-property name="maAcct1" type="java.lang.String">
                <column name="ma_acct1" length="80" />
            </key-property>
            <key-property name="maAcct2" type="java.lang.String">
                <column name="ma_acct2" length="80" />
            </key-property>
            <key-property name="maSub1" type="java.lang.String">
                <column name="ma_sub1" length="80" />
            </key-property>
            <key-property name="maSub2" type="java.lang.String">
                <column name="ma_sub2" length="80" />
            </key-property>
            <key-property name="maCc1" type="java.lang.String">
                <column name="ma_cc1" length="30" />
            </key-property>
            <key-property name="maCc2" type="java.lang.String">
                <column name="ma_cc2" length="30" />
            </key-property>
            <key-property name="maAllSub" type="java.lang.Boolean">
                <column name="ma_all_sub" />
            </key-property>
            <key-property name="maAllCc" type="java.lang.Boolean">
                <column name="ma_all_cc" />
            </key-property>
        </composite-id>
        <property name="maMrAcct1" type="java.lang.String">
            <column name="ma_mr_acct1" length="80" />
        </property>
        <property name="maMrCc1" type="java.lang.String">
            <column name="ma_mr_cc1" length="30" />
        </property>
        <property name="maMrAcct2" type="java.lang.String">
            <column name="ma_mr_acct2" length="80" />
        </property>
        <property name="maMrCc2" type="java.lang.String">
            <column name="ma_mr_cc2" length="30" />
        </property>
        <property name="maUser1" type="java.lang.String">
            <column name="ma_user1" length="80" />
        </property>
        <property name="maUser2" type="java.lang.String">
            <column name="ma_user2" length="80" />
        </property>
        <property name="maQadc01" type="java.lang.String">
            <column name="ma__qadc01" length="80" />
        </property>
        <property name="maMrSub1" type="java.lang.String">
            <column name="ma_mr_sub1" length="80" />
        </property>
        <property name="maMrSub2" type="java.lang.String">
            <column name="ma_mr_sub2" length="80" />
        </property>
        <property name="oidMaMstr" type="java.lang.Double">
            <column name="oid_ma_mstr" precision="38" scale="10" not-null="true" />
        </property>
    </class>
</hibernate-mapping>
