<?xml version="1.0" encoding="utf-8"?>
<!DOCTYPE hibernate-mapping PUBLIC "-//Hibernate/Hibernate Mapping DTD 3.0//EN"
"http://hibernate.sourceforge.net/hibernate-mapping-3.0.dtd">
<!-- 
    Mapping file autogenerated by MyEclipse Persistence Tools
-->
<hibernate-mapping>
    <class name="com.gopawpaw.erp.hibernate.k.KnbsDet" table="knbs_det" schema="PUB" catalog="MFGPROD">
        <composite-id name="id" class="com.gopawpaw.erp.hibernate.k.KnbsDetId">
            <key-property name="knbsKeyid" type="java.lang.Double">
                <column name="knbs_keyid" precision="38" scale="10" />
            </key-property>
            <key-property name="knbsSourceType" type="java.lang.String">
                <column name="knbs_source_type" length="16" />
            </key-property>
            <key-property name="knbsRef1" type="java.lang.String">
                <column name="knbs_ref1" length="16" />
            </key-property>
            <key-property name="knbsRef2" type="java.lang.String">
                <column name="knbs_ref2" length="16" />
            </key-property>
            <key-property name="knbsRef3" type="java.lang.String">
                <column name="knbs_ref3" length="16" />
            </key-property>
            <key-property name="knbsRef4" type="java.lang.String">
                <column name="knbs_ref4" length="16" />
            </key-property>
            <key-property name="knbsRef5" type="java.lang.String">
                <column name="knbs_ref5" length="16" />
            </key-property>
            <key-property name="knbsModDate" type="java.util.Date">
                <column name="knbs_mod_date" length="4" />
            </key-property>
            <key-property name="knbsModUserid" type="java.lang.String">
                <column name="knbs_mod_userid" length="16" />
            </key-property>
            <key-property name="knbsUser1" type="java.lang.String">
                <column name="knbs_user1" length="48" />
            </key-property>
            <key-property name="knbsUser2" type="java.lang.String">
                <column name="knbs_user2" length="48" />
            </key-property>
            <key-property name="knbsQadc01" type="java.lang.String">
                <column name="knbs__qadc01" length="48" />
            </key-property>
            <key-property name="knbsQadc02" type="java.lang.String">
                <column name="knbs__qadc02" length="48" />
            </key-property>
            <key-property name="knbsDomain" type="java.lang.String">
                <column name="knbs_domain" length="8" />
            </key-property>
            <key-property name="oidKnbsDet" type="java.lang.Double">
                <column name="oid_knbs_det" precision="38" scale="10" />
            </key-property>
        </composite-id>
    </class>
</hibernate-mapping>
