<?xml version="1.0" encoding="utf-8"?>
<!DOCTYPE hibernate-mapping PUBLIC "-//Hibernate/Hibernate Mapping DTD 3.0//EN"
"http://hibernate.sourceforge.net/hibernate-mapping-3.0.dtd">
<!-- 
    Mapping file autogenerated by MyEclipse Persistence Tools
-->
<hibernate-mapping>
    <class name="com.gopawpaw.erp.hibernate.c.CaqMstr" table="caq_mstr" schema="PUB" catalog="MFGPROD">
        <composite-id name="id" class="com.gopawpaw.erp.hibernate.c.CaqMstrId">
            <key-property name="caqDomain" type="java.lang.String">
                <column name="caq_domain" length="8" />
            </key-property>
            <key-property name="caqQue" type="java.lang.String">
                <column name="caq_que" length="80" />
            </key-property>
            <key-property name="caqFileType" type="java.lang.String">
                <column name="caq_file_type" length="80" />
            </key-property>
        </composite-id>
        <property name="caqDesc" type="java.lang.String">
            <column name="caq_desc" length="80" />
        </property>
        <property name="caqArea" type="java.lang.String">
            <column name="caq_area" length="80" />
        </property>
        <property name="caqNode" type="java.lang.String">
            <column name="caq_node" length="30" />
        </property>
        <property name="caqChr01" type="java.lang.String">
            <column name="caq__chr01" length="80" />
        </property>
        <property name="caqChr02" type="java.lang.String">
            <column name="caq__chr02" length="80" />
        </property>
        <property name="caqChr03" type="java.lang.String">
            <column name="caq__chr03" length="80" />
        </property>
        <property name="caqLog01" type="java.lang.Boolean">
            <column name="caq__log01" />
        </property>
        <property name="caqLog02" type="java.lang.Boolean">
            <column name="caq__log02" />
        </property>
        <property name="caqDte01" type="java.util.Date">
            <column name="caq__dte01" length="4" />
        </property>
        <property name="caqDte02" type="java.util.Date">
            <column name="caq__dte02" length="4" />
        </property>
        <property name="caqDec01" type="java.lang.Double">
            <column name="caq__dec01" precision="38" scale="10" />
        </property>
        <property name="caqDec02" type="java.lang.Double">
            <column name="caq__dec02" precision="38" scale="10" />
        </property>
        <property name="caqUser1" type="java.lang.String">
            <column name="caq_user1" length="80" />
        </property>
        <property name="caqUser2" type="java.lang.String">
            <column name="caq_user2" length="80" />
        </property>
        <property name="caq3rdParty" type="java.lang.Boolean">
            <column name="caq_3rd_party" not-null="true" />
        </property>
        <property name="caqAreaPri" type="java.lang.Boolean">
            <column name="caq_area_pri" not-null="true" />
        </property>
        <property name="caqAreaSc" type="java.lang.Boolean">
            <column name="caq_area_sc" not-null="true" />
        </property>
        <property name="caqCreateBom" type="java.lang.Boolean">
            <column name="caq_create_bom" not-null="true" />
        </property>
        <property name="caqCreateRte" type="java.lang.Boolean">
            <column name="caq_create_rte" not-null="true" />
        </property>
        <property name="caqCreateWo" type="java.lang.Boolean">
            <column name="caq_create_wo" not-null="true" />
        </property>
        <property name="caqDefaultRte" type="java.lang.String">
            <column name="caq_default_rte" length="80" not-null="true" />
        </property>
        <property name="caqField" type="java.lang.Boolean">
            <column name="caq_field" not-null="true" />
        </property>
        <property name="caqProbPri" type="java.lang.Boolean">
            <column name="caq_prob_pri" not-null="true" />
        </property>
        <property name="caqDepot" type="java.lang.Boolean">
            <column name="caq_depot" />
        </property>
        <property name="oidCaqMstr" type="java.lang.Double">
            <column name="oid_caq_mstr" precision="38" scale="10" not-null="true" />
        </property>
    </class>
</hibernate-mapping>
