<?xml version="1.0" encoding="utf-8"?>
<!DOCTYPE hibernate-mapping PUBLIC "-//Hibernate/Hibernate Mapping DTD 3.0//EN"
"http://hibernate.sourceforge.net/hibernate-mapping-3.0.dtd">
<!-- 
    Mapping file autogenerated by MyEclipse Persistence Tools
-->
<hibernate-mapping>
    <class name="com.gopawpaw.erp.hibernate.c.CilMstr" table="cil_mstr" schema="PUB" catalog="MFGPROD">
        <composite-id name="id" class="com.gopawpaw.erp.hibernate.c.CilMstrId">
            <key-property name="cilDomain" type="java.lang.String">
                <column name="cil_domain" length="8" />
            </key-property>
            <key-property name="cilCorInv" type="java.lang.String">
                <column name="cil_cor_inv" length="80" />
            </key-property>
            <key-property name="cilCorSoNbr" type="java.lang.String">
                <column name="cil_cor_so_nbr" length="80" />
            </key-property>
        </composite-id>
        <property name="cilCorRsn" type="java.lang.String">
            <column name="cil_cor_rsn" length="80" not-null="true" />
        </property>
        <property name="cilModUserid" type="java.lang.String">
            <column name="cil_mod_userid" length="80" not-null="true" />
        </property>
        <property name="cilModDate" type="java.util.Date">
            <column name="cil_mod_date" length="4" not-null="true" />
        </property>
        <property name="cilMstrInv" type="java.lang.String">
            <column name="cil_mstr_inv" length="80" not-null="true" />
        </property>
        <property name="cilPrevSoNbr" type="java.lang.String">
            <column name="cil_prev_so_nbr" length="80" not-null="true" />
        </property>
        <property name="cilPrevInv" type="java.lang.String">
            <column name="cil_prev_inv" length="80" not-null="true" />
        </property>
        <property name="cilUser1" type="java.lang.String">
            <column name="cil_user1" length="80" not-null="true" />
        </property>
        <property name="cilUser2" type="java.lang.String">
            <column name="cil_user2" length="80" not-null="true" />
        </property>
        <property name="cilQadc01" type="java.lang.String">
            <column name="cil__qadc01" length="80" not-null="true" />
        </property>
        <property name="cilQadc02" type="java.lang.String">
            <column name="cil__qadc02" length="80" not-null="true" />
        </property>
        <property name="oidCilMstr" type="java.lang.Double">
            <column name="oid_cil_mstr" precision="38" scale="10" not-null="true" />
        </property>
    </class>
</hibernate-mapping>
